optimusnlp/__init__.py
optimusnlp/data/ner.txt
optimusnlp-0.1.dist-info/METADATA
optimusnlp-0.1.dist-info/WHEEL
optimusnlp-0.1.dist-info/top_level.txt
optimusnlp-0.1.dist-info/RECORD
