Metadata-Version: 2.1
Name: optimusnlp
Version: 0.1
Summary: A package that includes a NER dataset.
Home-page: https://github.com/yourusername/my_package
Author: John doe
Author-email: your.email@example.com
License: MIT
Platform: UNKNOWN
Classifier: Development Status :: 3 - Alpha
Classifier: Intended Audience :: Developers
Classifier: License :: OSI Approved :: MIT License
Classifier: Programming Language :: Python :: 3.6
Classifier: Programming Language :: Python :: 3.7
Classifier: Programming Language :: Python :: 3.8
Classifier: Programming Language :: Python :: 3.9
